{
  "global_percentage": 29.0,
  "by_technology": {
    "solar": 3.0,
    "wind": 7.0,
    "hydro": 16.0,
    "nuclear": 10.0,
    "other_renewables": 3.0
  },
  "top_countries": [
    {
      "country": "Norway",
      "percentage": 98.0
    },
    {
      "country": "Iceland",
      "percentage": 95.0
    },
    {
      "country": "Brazil",
      "percentage": 83.0
    },
    {
      "country": "Austria",
      "percentage": 78.0
    },
    {
      "country": "Sweden",
      "percentage": 74.0
    },
    {
      "country": "Switzerland",
      "percentage": 69.0
    },
    {
      "country": "France",
      "percentage": 68.0
    },
    {
      "country": "New Zealand",
      "percentage": 67.0
    },
    {
      "country": "Portugal",
      "percentage": 66.0
    },
    {
      "country": "Denmark",
      "percentage": 65.0
    }
  ],
  "year_over_year_growth": 2.5,
  "data_source": "IEA, EIA, Ember Climate Global Electricity Database, Our World in Data",
  "last_updated": "2024-10-01",
  "timestamp": "2025-12-09T11:14:48.307434"
}