{
  "nvidia": {
    "h100": {
      "manufacturing_cost": null,
      "suggested_retail": null,
      "gross_margin": null,
      "cost_breakdown": {
        "silicon": null,
        "packaging": null,
        "testing": null,
        "r_and_d_allocation": null
      }
    },
    "a100": {
      "manufacturing_cost": null,
      "suggested_retail": null,
      "gross_margin": null,
      "cost_breakdown": {
        "silicon": null,
        "packaging": null,
        "testing": null,
        "r_and_d_allocation": null
      }
    }
  },
  "amd": {
    "mi300x": {
      "manufacturing_cost": null,
      "suggested_retail": null,
      "gross_margin": null
    }
  },
  "intel": {
    "arc_gpu": {
      "manufacturing_cost": null,
      "suggested_retail": null,
      "gross_margin": null
    }
  },
  "industry_analysis": {
    "average_gross_margin": null,
    "cost_trend": "Specific detailed cost trends for 2024-2025 are not publicly available.",
    "main_cost_driver": "Advanced packaging (e.g., CoWoS), wafer prices, and R&D remain primary cost drivers."
  },
  "last_updated": "2024-07-20",
  "timestamp": "2025-12-12T03:57:13.686676"
}