{
  "updated_at": "2025-12-09T18:15:44.442453",
  "source": "Yahoo Finance API (Direct)",
  "note": "直接 API 调用，100% 精确",
  "prices": {
    "NVDA": {
      "symbol": "NVDA",
      "price": 184.89,
      "previous_close": 185.5500030517578,
      "change": -0.66,
      "change_percent": -0.36,
      "currency": "USD",
      "exchange": "NMS",
      "market_state": "unknown",
      "timestamp": "2025-12-09T18:15:42.786384",
      "source": "Yahoo Finance API"
    },
    "AMD": {
      "symbol": "AMD",
      "price": 222.68,
      "previous_close": 221.11000061035156,
      "change": 1.57,
      "change_percent": 0.71,
      "currency": "USD",
      "exchange": "NMS",
      "market_state": "unknown",
      "timestamp": "2025-12-09T18:15:42.861068",
      "source": "Yahoo Finance API"
    },
    "GOOGL": {
      "symbol": "GOOGL",
      "price": 317.55,
      "previous_close": 313.7200012207031,
      "change": 3.83,
      "change_percent": 1.22,
      "currency": "USD",
      "exchange": "NMS",
      "market_state": "unknown",
      "timestamp": "2025-12-09T18:15:42.937065",
      "source": "Yahoo Finance API"
    },
    "AAPL": {
      "symbol": "AAPL",
      "price": 278.54,
      "previous_close": 277.8900146484375,
      "change": 0.65,
      "change_percent": 0.23,
      "currency": "USD",
      "exchange": "NMS",
      "market_state": "unknown",
      "timestamp": "2025-12-09T18:15:43.065639",
      "source": "Yahoo Finance API"
    },
    "AMZN": {
      "symbol": "AMZN",
      "price": 228.26,
      "previous_close": 226.88999938964844,
      "change": 1.37,
      "change_percent": 0.6,
      "currency": "USD",
      "exchange": "NMS",
      "market_state": "unknown",
      "timestamp": "2025-12-09T18:15:43.126148",
      "source": "Yahoo Finance API"
    },
    "MSFT": {
      "symbol": "MSFT",
      "price": 490.1,
      "previous_close": 491.0199890136719,
      "change": -0.92,
      "change_percent": -0.19,
      "currency": "USD",
      "exchange": "NMS",
      "market_state": "unknown",
      "timestamp": "2025-12-09T18:15:43.253548",
      "source": "Yahoo Finance API"
    },
    "META": {
      "symbol": "META",
      "price": 656.19,
      "previous_close": 666.7999877929688,
      "change": -10.61,
      "change_percent": -1.59,
      "currency": "USD",
      "exchange": "NMS",
      "market_state": "unknown",
      "timestamp": "2025-12-09T18:15:43.332499",
      "source": "Yahoo Finance API"
    },
    "TSLA": {
      "symbol": "TSLA",
      "price": 450.779,
      "previous_close": 439.5799865722656,
      "change": 11.2,
      "change_percent": 2.55,
      "currency": "USD",
      "exchange": "NMS",
      "market_state": "unknown",
      "timestamp": "2025-12-09T18:15:43.398388",
      "source": "Yahoo Finance API"
    },
    "BIDU": {
      "symbol": "BIDU",
      "price": 124.202,
      "previous_close": 130.05999755859375,
      "change": -5.86,
      "change_percent": -4.5,
      "currency": "USD",
      "exchange": "NMS",
      "market_state": "unknown",
      "timestamp": "2025-12-09T18:15:43.466268",
      "source": "Yahoo Finance API"
    },
    "BABA": {
      "symbol": "BABA",
      "price": 156.154,
      "previous_close": 158.1300048828125,
      "change": -1.98,
      "change_percent": -1.25,
      "currency": "USD",
      "exchange": "NYQ",
      "market_state": "unknown",
      "timestamp": "2025-12-09T18:15:43.537238",
      "source": "Yahoo Finance API"
    },
    "JD": {
      "symbol": "JD",
      "price": 29.355,
      "previous_close": 29.920000076293945,
      "change": -0.57,
      "change_percent": -1.89,
      "currency": "USD",
      "exchange": "NMS",
      "market_state": "unknown",
      "timestamp": "2025-12-09T18:15:43.645238",
      "source": "Yahoo Finance API"
    },
    "PDD": {
      "symbol": "PDD",
      "price": 115.7,
      "previous_close": 117.62000274658203,
      "change": -1.92,
      "change_percent": -1.63,
      "currency": "USD",
      "exchange": "NMS",
      "market_state": "unknown",
      "timestamp": "2025-12-09T18:15:43.709033",
      "source": "Yahoo Finance API"
    },
    "NTES": {
      "symbol": "NTES",
      "price": 136.065,
      "previous_close": 136.86000061035156,
      "change": -0.8,
      "change_percent": -0.58,
      "currency": "USD",
      "exchange": "NMS",
      "market_state": "unknown",
      "timestamp": "2025-12-09T18:15:43.787406",
      "source": "Yahoo Finance API"
    },
    "BILI": {
      "symbol": "BILI",
      "price": 25.02,
      "previous_close": 26.0,
      "change": -0.98,
      "change_percent": -3.77,
      "currency": "USD",
      "exchange": "NMS",
      "market_state": "unknown",
      "timestamp": "2025-12-09T18:15:43.866959",
      "source": "Yahoo Finance API"
    },
    "NIO": {
      "symbol": "NIO",
      "price": 5.036,
      "previous_close": 5.099999904632568,
      "change": -0.06,
      "change_percent": -1.25,
      "currency": "USD",
      "exchange": "NYQ",
      "market_state": "unknown",
      "timestamp": "2025-12-09T18:15:43.926327",
      "source": "Yahoo Finance API"
    },
    "XPEV": {
      "symbol": "XPEV",
      "price": 19.705,
      "previous_close": 20.520000457763672,
      "change": -0.82,
      "change_percent": -3.97,
      "currency": "USD",
      "exchange": "NYQ",
      "market_state": "unknown",
      "timestamp": "2025-12-09T18:15:44.006976",
      "source": "Yahoo Finance API"
    },
    "LI": {
      "symbol": "LI",
      "price": 17.215,
      "previous_close": 17.950000762939453,
      "change": -0.74,
      "change_percent": -4.09,
      "currency": "USD",
      "exchange": "NMS",
      "market_state": "unknown",
      "timestamp": "2025-12-09T18:15:44.088099",
      "source": "Yahoo Finance API"
    },
    "EDU": {
      "symbol": "EDU",
      "price": 53.055,
      "previous_close": 53.90999984741211,
      "change": -0.85,
      "change_percent": -1.59,
      "currency": "USD",
      "exchange": "NYQ",
      "market_state": "unknown",
      "timestamp": "2025-12-09T18:15:44.168984",
      "source": "Yahoo Finance API"
    },
    "TCEHY": {
      "symbol": "TCEHY",
      "price": 76.95,
      "previous_close": 77.7699966430664,
      "change": -0.82,
      "change_percent": -1.05,
      "currency": "USD",
      "exchange": "PNK",
      "market_state": "unknown",
      "timestamp": "2025-12-09T18:15:44.248780",
      "source": "Yahoo Finance API"
    },
    "MPNGY": {
      "symbol": "MPNGY",
      "price": 24.89,
      "previous_close": 25.489999771118164,
      "change": -0.6,
      "change_percent": -2.35,
      "currency": "USD",
      "exchange": "PNK",
      "market_state": "unknown",
      "timestamp": "2025-12-09T18:15:44.316205",
      "source": "Yahoo Finance API"
    },
    "XIACY": {
      "symbol": "XIACY",
      "price": 26.4,
      "previous_close": 27.299999237060547,
      "change": -0.9,
      "change_percent": -3.3,
      "currency": "USD",
      "exchange": "PNK",
      "market_state": "unknown",
      "timestamp": "2025-12-09T18:15:44.377813",
      "source": "Yahoo Finance API"
    }
  }
}